{
  "channel": {
    "id": "bogxd",
    "name": "Bog",
    "profile": "https://yt3.googleusercontent.com/DhnqwJyF99ahfp4jJ4XR3-Hf4HWWyoqyOJHQTBiv4i5yODohfEo8jE5PXLJqhQf__2ocq0Lx=s176-c-k-c0x00ffffff-no-rj",
    "banner": "https://yt3.googleusercontent.com/w1UhRLQ3iMRVEfnDg3X8VE2EYvlteY5Gaksfm2l2wwa_xKl2TvULh7Bub1tvlmJFLHIXmrF5pdw=w1707-fcrop64=1,00005a57ffffa5a8-k-c0xffffffff-no-nd-rj"
  },
  "videos": [
    { "id": "5anTYHWuMSA", "title": "The Manim Experience - Creating animations with Python" },
    { "id": "h4ZQfr-q3EA", "title": "The Vim Experience" },
    { "id": "uZDPXFQYz0Q", "title": "Arch Linux Experience - Hyprland" },
    { "id": "UUuoi_huVfA", "title": "Trying \"Free Photoshop\" - Photopea" },
    { "id": "cMeIy7ryLBM", "title": "Best Mac Apps" },
    { "id": "xyWjNLR6OQI", "title": "The AutoHotkey Experience" },
    { "id": "Uju7Nz6CU5E", "title": "The CapCut Experience (as an Adobe user)" },
    { "id": "o3nBbvfdwkI", "title": "How I Beat The Password Game" },
    { "id": "DbgvDGtjkEA", "title": "Somebody emailed me a trojan virus" },
    { "id": "8WkcLwXCFJQ", "title": "The Linux Experience" },
    { "id": "XSr1czRjJnw", "title": "How to STAND OUT on YouTube" },
    { "id": "urYjGtnfckM", "title": "The ARCH LINUX Experience" },
    { "id": "T6UbJp6Abrc", "title": "How to make videos as a side hustle" },
    { "id": "qsAM8ycpTA8", "title": "How To Become An S Tier Mac User" },
    { "id": "LmZTpvHD_nU", "title": "100% battery health after 311 days (10 months). Here's how" },
    { "id": "v8vJFQHNn_c", "title": "How To Make Windows More Like MacOS" },
    { "id": "4VhJSxMKIqM", "title": "The Windows App Iceberg" },
    { "id": "l8aKnu1JC20", "title": "How I Set Up Adobe Premiere Pro For EDITING FAST" },
    { "id": "yYJOE6qXoDk", "title": "8 Simple Habits That Consistently Make Me Money" },
    { "id": "Bf7bO9VeePA", "title": "MacOS Is Horrible Until You Learn How To Use It" },
    { "id": "LLUrxMWdVqU", "title": "The ULTIMATE MacOS Keyboard Shortcut Tier List" }
  ],
  "playlists": [

  ]
}