{
  "channel": {
    "id": "Britec09",
    "name": "Britec09",
    "profile": "https://yt3.googleusercontent.com/ytc/AGIKgqOGgxDvO4EOPacWD86VmsWqUPHmSed6-6vC2eCGVw=s176-c-k-c0x00ffffff-no-rj",
    "banner": "https://yt3.googleusercontent.com/hMmPjo5BEvqJ76_IVIYxNbXsTKR3GCaiVQu6dNj0sFDQYzZ0wou1vIas42KLW992CditOVvpBg=w1060-fcrop64=1,00005a57ffffa5a8-k-c0xffffffff-no-nd-rj"
  },
  "videos": [
    { "id": "6w_0EPryF9w", "title": "Convert NTFS to FAT32 or FAT32 to NTFS Without Data Loss" },
    { "id": "_Aejs2MnG2M", "title": "Windows 11 Right Click Context Menu is Junk" },
    { "id": "_RrmqbgWQLE", "title": "What Makes Linux Better Than Windows" },
    { "id": "2ceiUTq6BHw", "title": "Do This When Installing Windows 11" },
    { "id": "f5Hp3dpIkfI", "title": "What Settings To Turn Off in Windows 11" },
    { "id": "tYeJXWpwaVg", "title": "Install Windows 11 With A Local Account" },
    { "id": "ur6Gf3NMnVY", "title": "4 Ways to Block USB Devices on Windows" },
    { "id": "Sl8MGskkVkA", "title": "Microsoft Edge’s NEW Scareware Blocker to Block Scammers" },
    { "id": "9lEBWKT_ZxU", "title": "Backup Software For Windows 10 and Windows 11" },
    { "id": "9ewhCutyZFc", "title": "Must Have 7 in 1 Smart Hub with M 2 SSD Enclosure" },
    { "id": "2FJ-o3Vde3c", "title": "What CPU Power Headers Do I Use" },
    { "id": "6n-dEmBv2rM", "title": "Snipping Tool Features You Need to Know" },
    { "id": "md1buL1d334", "title": "How to Create a Hyper V Virtual Machine With PowerShell" },
    { "id": "RQ19waIxaqw", "title": "Download and Install Office 2024 From Microsoft For Free" },
    { "id": "3ezuZrvE71M", "title": "The Ultimate Clean Windows 11 Install Guide" },
    { "id": "l4kUUsgKiiY", "title": "Get Legit Microsoft Office For 100% Free" },
    { "id": "LlAhFSrrVMM", "title": "How to Prevent Normal User From Installing Apps" },
    { "id": "D7Fp0gJaXnM", "title": "Turn Mini PC Into A Minecraft Server" },
    { "id": "Az7-lMftbxE", "title": "The New Way To Setup Windows 11" },
    { "id": "5l51NwidHK4", "title": "Display System Resource Usage on Windows 11 Taskbar" },
    { "id": "-yDQGP4WSHU", "title": "Optimize Windows 11 to Boost Performance With No Software" },
    { "id": "RF9uFaU7MsY", "title": "File Explorer Not Responding, Crashing or Freezing Fix in Windows 11" },
    { "id": "oFfNP2QkVo4", "title": "World's Smallest Server That Everyone Needs" },
    { "id": "uYr4MsZpXOA", "title": "How to Join The Britec Discord Server For A Chat and Free Tech Support" },
    { "id": "wiCS3E77u2M", "title": "How to Debloat Windows 11 For Optimal Performance" },
    { "id": "T6xSEyk4LGA", "title": "Microsoft Drops Support for Intel 8th, 9th, and 10th Gen CPUs for Windows 11 24H2" },
    { "id": "4g0MdCzcu1U", "title": "BEST Budget NAS GMKTec NucBox G9 NAS Review" },
    { "id": "sv391yBARlI", "title": "Microsoft is Making A New PC Migration App For Windows 11" },
    { "id": "xFvzjvlo6WQ", "title": "How to Setup Network Attached Storage (NAS) in 2025" },
    { "id": "1B60ydt0gMs", "title": "This Windows 11 Start Menu Makes It Better For Free" },
    { "id": "07R6nDFrNNo", "title": "Why The Hate? Was I Wrong?" },
    { "id": "G30DD7tWYdU", "title": "Stop Windows Updates Destroying Your Laptop" },
    { "id": "dzkl6ZCQO9s", "title": "Best Free Automated Backup Solution Everyone Should Use" },
    { "id": "hKCcovnXqfk", "title": "Replace Big Office PC With This ASUS NUC 14 Pro" },
    { "id": "QRW7DM-7Fy4", "title": "FREE Malware Removal Tools That Remove Viruses" },
    { "id": "h8JRDXH_PHk", "title": "Installing Windows 11? Do This First?" },
    { "id": "FQNPmQVuaNI", "title": "Stop Files Automatically Uploading To OneDrive" },
    { "id": "9yzB1Lva9Iw", "title": "PC Powers On But NO Display | Motherboard DRAM Light On" },
    { "id": "sIEY7YEhQNc", "title": "Disable Internet Connection Without Disabling The LAN Network" },
    { "id": "0fDY_SATDWg", "title": "The Software You Wish You knew" },
    { "id": "z8ZFHLLZ5H4", "title": "Will Microsoft Change Windows 11 Requirements" },
    { "id": "S3XLeTGjOXs", "title": "Microsoft Forcing Automatic Update to Windows 11 24H2" },
    { "id": "-xN8vMTA8xs", "title": "Can't Delete A File or Folder? Do this" },
    { "id": "hpMg_99YwKs", "title": "Microsoft Will Automatically Keep You Signed in Your Microsoft Account" },
    { "id": "BHUAEFauh7k", "title": "Upgrade to Windows 11 on Unsupported Hardware The Easiest Way" },
    { "id": "L0cNJxezv7k", "title": "Block Any Program From Running in Windows 11" },
    { "id": "ossZ7cJvgrk", "title": "Building A Gaming PC in the HYTE Y70 | 7800X3D | 4080 Super" },
    { "id": "x3_jDmy7mo4", "title": "Mini PC That Packs A Punch | Geekom GT1 MEGA Ultra 9" },
    { "id": "ZirucbhTOng", "title": "Signs That Your Web Browser May Have Been Hacked" },
    { "id": "TfUjB7k59kE", "title": "Microsoft Now Allowing Windows 11 on Unsupported Hardware" },
    { "id": "4UmnJNL1SKQ", "title": "Install Windows 11 on Unsupported PC The Official Way" },
    { "id": "3YqbfjevWdc", "title": "Will Your PC Support Windows 11 24H2" },
    { "id": "DGeQS3fL0Cs", "title": "Enable Private Web Browsing on Windows 11" },
    { "id": "ZVpvYH86RXE", "title": "Upgrade to Windows 11 on Old Computers Without Losing Programs" },
    { "id": "WzxCp_NLAPs", "title": "Change This Setting if You Upgrade to Windows 11" },
    { "id": "cB2ldI8XweY", "title": "EVERY Windows 11 User Should Have THIS Free Optimization Tool" },
    { "id": "gEujENwhG7A", "title": "Take Control of Your Network Connections in Windows" },
    { "id": "kcPh_GYcCVU", "title": "Fix NAS Error 0x80070035 After Windows 11 24H2 Update" },
    { "id": "5fTl_R7rAK8", "title": "Windows Commands You Should Know" },
    { "id": "Htn0KmQfSp0", "title": "Fix Windows 11 Update Error Problems" },
    { "id": "CTImcBp9uo0", "title": "How to Download Any Windows ISO Version" },
    { "id": "MJjxhq0PRyM", "title": "EVERY Windows User Should Use THIS Free Software" },
    { "id": "75Hg866SJI0", "title": "Windows 11 24H2 Install on Unsupported Hardware with Rufus" },
    { "id": "xdhppLSqZus", "title": "Install Any Operating System Like A Pro" },
    { "id": "cMY-nBnljTc", "title": "Stay on Windows 10 AFTER Support Ends" },
    { "id": "FAmV4jy-tEY", "title": "How To DEBLOAT Windows to Remove Copilot Recall Telemetry" },
    { "id": "66MNDLMAn30", "title": "ZimaCube Pro, The Perfect Home Server?" },
    { "id": "Tx_ZNWTiGHY", "title": "Windows 11 24H2 LTSC The BEST Version of Windows" },
    { "id": "abQifxq3HhU", "title": "Turn Your Old Windows PC into File Sharing Server For Free" },
    { "id": "0iopGu-WJ2U", "title": "Install Missing Microsoft Store on Windows 11 LTSC 24H2" },
    { "id": "lNoZ4GzHbxU", "title": "How to Migrate or Clone Windows to Another SSD NVME Drive" },
    { "id": "lrYR8PuF84Y", "title": "How to Completely Remove Software That Won't Uninstall" },
    { "id": "KfUbCR_Tuuo", "title": "Windows 10 End of Life - Everything You Need to Know" },
    { "id": "xwv41exScnM", "title": "Stop The Most Annoying Feature of Windows Notepad" },
    { "id": "ku_MLSVUM2E", "title": "Access Android Phone Storage Directly in Windows 11 File Explorer No USB" },
    { "id": "HNXri_3naV8", "title": "Disable Microsoft Windows Telemetry Like Copilot Recall The Safe Way" },
    { "id": "ycKZZ9pSeag", "title": "Useful App For Permanently Deleting Files Beyond Recovery" },
    { "id": "IntHAgmAFkU", "title": "Install FydeOS on Any Old Laptop or PC | ChromeOS Alternative" },
    { "id": "TDBH6VrRjf4", "title": "Setup Windows 11 Settings in Seconds No Software Needed" },
    { "id": "5gLRhVimYuA", "title": "Make A Custom Windows 11 ISO with MicroWin" },
    { "id": "s8VkAYPEbFU", "title": "Can We Safely Uninstall Microsoft Edge Yet?" },
    { "id": "Hu1CvS5cYjA", "title": "5 Common Ways of Getting a Computer Virus" },
    { "id": "DrcK2DfGVvg", "title": "The Perfect Network Attached Storage Asustor LOCKERSTOR 4 Gen3 AS6804T" },
    { "id": "QF_QHg3ZEQs", "title": "Microsoft Edge WebView2 Runtime is Missing?" },
    { "id": "Qp5WTWIFNtc", "title": "The Mini PC That Everyone Has Been Waiting For" },
    { "id": "tc76m-nTunM", "title": "Can Your Old PC Handle The Windows 11 Upgrade" },
    { "id": "nABsMn5b9Lw", "title": "Stay On Windows 10 Until 2032 With LTSC ?" },
    { "id": "Zk_KfKg2pt4", "title": "Create A File Server For FREE with No Software" },
    { "id": "S4SGxnirSVo", "title": "Google Has NEW Android Emulator for Apps & Games on PC" },
    { "id": "9_Pr-M11mcg", "title": "These Two Windows Setting Could Fix Your PC" },
    { "id": "7gEziIskT3w", "title": "Windows 11 Settings You Need To Change" },
    { "id": "apk7QSxAGXg", "title": "Simply The Best Mini PC You Can Buy" },
    { "id": "1dURsMBWPxA", "title": "Stop Doing This To Windows 11 or Windows 10" },
    { "id": "1w61dAcEkdM", "title": "Microsoft Now Allows Customization Apps on Windows 11 24H2" },
    { "id": "CkPy0B3HjhI", "title": "Windows 11 24H2 Feature Update Causing BSOD Problem" },
    { "id": "ELHotbPL1ec", "title": "Should You Update To Windows 11 24H2 Right Now" },
    { "id": "Ksqe6HKuJy0", "title": "Stop Windows From Automatically Locking Itself" },
    { "id": "i-AcLkLSnYM", "title": "Change These Settings to Maximize Your Laptop's Battery Life" },
    { "id": "uo6ATWUWCh4", "title": "Windows 11 In Place Upgrade & Repair Install" },
    { "id": "0gfiAEi4X24", "title": "Microsoft Edge Settings to Change to Enhance Browsing Experience" },
    { "id": "5Ucy7ESbbUs", "title": "How to Check if Your Wi-Fi is Being Used Without Your Permission" },
    { "id": "BHD-AmK_XIo", "title": "Windows Recall Coming to Every PC ?" },
    { "id": "jnm4nncMj9o", "title": "Microsoft NEW AI Photos App Slows Your PC Down - Lets FIX IT" },
    { "id": "eec4ntD5Qoo", "title": "Adminless Windows 11 For Better PC Security" },
    { "id": "C8-JC_W32kU", "title": "Can We Really Stop Microsoft Spying on Windows 11" },
    { "id": "7YH5n4exg8I", "title": "Tweak Hidden Windows Registry Settings With One Click" },
    { "id": "B8I0c2q_R4U", "title": "Need Windows 11 24H2 Now Change This Windows Update Setting" },
    { "id": "iAB7LSD5Bss", "title": "Windows Update Not Working? Do This!" },
    { "id": "KbxzbABjLYY", "title": "Stop Microsoft Windows Spying in 1 Minute" },
    { "id": "J28fBWeEYtc", "title": "Crowdstrike Windows Update Causes Major Computer Outages Worldwide" },
    { "id": "WmMIaEe2-Eo", "title": "The Privacy App All Windows 11 Users Must Have" },
    { "id": "URks20NnGRw", "title": "Setup a CHEAP Homelab Linux Server With CasaOS" },
    { "id": "oJlQiZxEoD4", "title": "5 Ways to Check GPU Health in Windows 11" },
    { "id": "EBH51JQvGdA", "title": "Windows Update Locks Users Out Of Computer" },
    { "id": "-GPjDU9dalk", "title": "Microsoft Release USB Boot Tool to Fix CrowdStrike Disaster" },
    { "id": "MZ4atmdvuPM", "title": "How to Choose The Right Linux Distro" },
    { "id": "aByK1nw2I3Y", "title": "Windows Gets Linux SUDO Command - Available in 24H2" },
    { "id": "j7EDZMrZQdE", "title": "Download and Install Office 2024 From Microsoft" },
    { "id": "gahb2gfVCz4", "title": "10 Windows Practices EVERY user should do NOW!" },
    { "id": "v09GYUE3YBg", "title": "Never Pay For Microsoft Office Software Again" },
    { "id": "hut_l0iEJA8", "title": "Fix Corrupt Registry in Windows 11" },
    { "id": "Tj15vlOPoyQ", "title": "Should You Enable Or Disable Core Isolation Protection" },
    { "id": "SJTj4v5rUPQ", "title": "What To Do After Installing Windows 11" },
    { "id": "F2djEpXdp1s", "title": "Your PC needs to be repaired Windows 10/11 - Fix UEFI Won't Boot" },
    { "id": "2QYPfyBV0YY", "title": "Buying A Mini PC? Watch This Video First - MinisForum UM890 Pro" },
    { "id": "Y1Nwr5sW_m0", "title": "Tiny Flash NVMe NAS Drive AIFFRO K100" },
    { "id": "yM4JLkWt4Ac", "title": "Windows Update Flaws Allow Undetectable Downgrade Attacks" },
    { "id": "kcmVdHRU9IM", "title": "This Mini PC is Perfect Home Server for Beginners" },
    { "id": "_9ClvlXUP3Q", "title": "This Windows Trick Saved My SSD" },
    { "id": "VjmKH2vJ3Lg", "title": "100% Disk Usage in Windows Solved" },
    { "id": "Rps5tn-xoD8", "title": "How To Transfer Windows Product Activation License Key" },
    { "id": "n9BLWVw3htU", "title": "Download and Install Office From Microsoft Account" },
    { "id": "0qAbJszgCwc", "title": "How to Fix No Power Plan Options Available on Windows 11" },
    { "id": "nM72j0LuUFM", "title": "How to Convert Video Files for FREE With VLC Media Player" },
    { "id": "cfS9HIomAmc", "title": "How to Stop Windows Update While in Progress" },
    { "id": "g35xUmITOaU", "title": "Create a Windows 11 Image Using DISM" },
    { "id": "YTNRrEU8kkM", "title": "Fix 0x80070643 Windows Update Error In Windows 11/10" },
    { "id": "0agwR7ev7cU", "title": "Fix Screen Rotation Lock Grayed Out on Windows 11 or Windows 10" },
    { "id": "z4w0OYi5L4M", "title": "How to Upgrade and Install Powershell 7 on Windows 11" },
    { "id": "8xp1-oScrJs", "title": "Install Windows Updates From PowerShell" },
    { "id": "Luu9xlA7XD0", "title": "Reset All Local Group Policy Settings to Default in Windows 11" },
    { "id": "gCx-hegNNko", "title": "Uninstall and Disable SMBv1 in Windows 10 & Windows 11" },
    { "id": "3iIGBT1zL7Y", "title": "BEST Free Disk Backup & Cloning Software Suite" },
    { "id": "xMgBLW8JppU", "title": "Slow Virtualization On Windows 11 VMware Workstation Fix" },
    { "id": "5g8-3zXJlP4", "title": "Make Windows Defender Antivirus More Secure" },
    { "id": "W6ZWB9fEr6w", "title": "Microsoft Confirms That Windows 11 Recall Feature Can't Be Uninstalled" },
    { "id": "rJFozoLwCaw", "title": "How to Use Firewall To Block Hackers and Malware" },
    { "id": "loN0QaQzdp0", "title": "Turn Your Orange Pi 5 Max into a Home Server With OpenMediaVault" },
    { "id": "1pmlSIyCkBg", "title": "Install Any Operating System Over Network with iVentoy" },
    { "id": "nUOmuN-7-d4", "title": "Install and Configure Ubuntu Server - Full Setup Guide" },
    { "id": "s29jN-8W8Nc", "title": "This Trick Can Recover Lost Hard Drive Partition to Recover Data" },
    { "id": "_tbvLSskiho", "title": "Run Android TV from USB On Your PC" },
    { "id": "5LNTy3seALA", "title": "NAS of the Future - The 8 Bay SSD Terramaster F8 SSD Plus" },
    { "id": "MKF-CFCD368", "title": "Outlook Users Should Change These Settings Now" },
    { "id": "QnsIcS5gnE4", "title": "Install Chrome OS On Any Old PC or Laptop With Play Store" },
    { "id": "XbMTcotH2lQ", "title": "How to Reduce Video File Size Without Losing Image Quality" },
    { "id": "uBDmi1q5klM", "title": "This Office Mini PC Has Everything You Need" },
    { "id": "rnyuY9xuTg4", "title": "How to Transfer Photos & Videos From Phone to Laptop or Desktop PC" },
    { "id": "iJReC-VvFXQ", "title": "How To CLEAN Install NVidia GPU Graphics Drivers" },
    { "id": "HvDMhU7Eu3Q", "title": "Share Folders & Drives From One Computer to Another Computer" },
    { "id": "IUunGXQ_yp0", "title": "The Perfect Storage Device for Everyone - F4 424 MAX" },
    { "id": "qP6VnpB8U7w", "title": "How to Delete NVIDIA Cache to FIX Game Stutter in Windows" },
    { "id": "klzZrW8BQUE", "title": "Stop Using Customization Apps on Windows 11" },
    { "id": "U4mrZTccnfM", "title": "Build an Awesome AMD 8700G Home Theatre Mini PC" },
    { "id": "-GQEMGXQ3is", "title": "Your Data on Discord Is Being Sold" },
    { "id": "eVRkM3hpfoQ", "title": "Windows PC Fails to POST with No Display" },
    { "id": "DzmGSZszX94", "title": "Your Own Private Network Attached Storage Solution by UGREEN" },
    { "id": "Eu6zViY3sbo", "title": "Microsoft Account Bypass Now Being Blocked During Setup" },
    { "id": "Qf7fZhzotA0", "title": "Update Motherboard BIOS Without A CPU Using Q Flash Button" },
    { "id": "dTWFajBRo_Y", "title": "Windows 10 Annoyances and How to FIX Them" },
    { "id": "YcQfNYX5Vi8", "title": "3 Ways to Clear Motherboard CMOS (Reset BIOS)" },
    { "id": "ThJcmITFpbo", "title": "Why is Windows 11 So BAD" },
    { "id": "-0U1gq8xX0s", "title": "What Can You Do About Windows Privacy" },
    { "id": "Zb4nw6flU6c", "title": "My Perfect Windows 11 Setup" },
    { "id": "271Bs5Hf2IE", "title": "Repair Corrupted Windows 11 System WITHOUT a PC Reset" },
    { "id": "MyG3m_WxyLc", "title": "Microsoft To Force BitLocker Encryption on Windows 11" },
    { "id": "j_T1DNjNF84", "title": "You Can Still Bypass Microsoft Account on Windows 11" },
    { "id": "Q3TnVAPPqac", "title": "Setup Windows 11 PC Without Microsoft Account" },
    { "id": "Z98_FDFKNSs", "title": "Change These Windows Settings Right Now" },
    { "id": "VLUbxakvu0o", "title": "Disable Forced BitLocker Encryption During Windows 11 Installation" },
    { "id": "00q7yVhpkVo", "title": "Windows 11 Will Now Record EVERYTHING You Do" },
    { "id": "zu2o7adKVKo", "title": "Everyone Needs This Windows 11 Bootable USB Installer" },
    { "id": "0hx4ums7KvI", "title": "Block Users From Opening Certain Programs on Windows 11" },
    { "id": "O47TOLk3580", "title": "Windows 11 User? Watch This Video" },
    { "id": "DZtNUeFt0QA", "title": "Time To Switch To Linux?" },
    { "id": "l8KwCdoKy6w", "title": "Microsoft Made An Alternative to CCleaner" },
    { "id": "x09PUo5C9eU", "title": "How to Create a Custom Windows 11 ISO" },
    { "id": "DMA4J9I4nS8", "title": "Modify Windows 11 ISO to Bypass TPM and Secure Boot on Unsupported PC" },
    { "id": "ExOXTjFNbfg", "title": "Your PC is Recording Everything You Do With Windows Recall" },
    { "id": "5EUcx53TBR8", "title": "Delete Undeletable Files or Folders in Windows 11" },
    { "id": "VmiKFdNxDJs", "title": "Disable Windows Recall and Copilot+ on Windows 11" },
    { "id": "4ljqh8Nyvh0", "title": "Say Goodbye to Windows Recall on Copilot+ PC" },
    { "id": "ESwDc57D620", "title": "Avoid Making This PC Mistake" },
    { "id": "K5naSG3Tki0", "title": "Migrate Windows to Another SSD Drive For FREE" },
    { "id": "Iq-epl4H-5I", "title": "Windows Flaw Lets Hackers Access Your PC Over Wi-Fi" },
    { "id": "AKyR91-6dhQ", "title": "Microsoft Reopen Feature Updates For Windows 10" },
    { "id": "P7hcuukdq6g", "title": "Windows 10 Users Need To Change This Setting NOW!" },
    { "id": "M3zmzGLVRNk", "title": "Change These Facebook Settings Right Now" },
    { "id": "HJI1_0Hy9VI", "title": "Things That Would Make Windows Good Again" },
    { "id": "DemlaQGW3Hw", "title": "What Is Taking Up So Much RAM Memory" },
    { "id": "hcWcXiI3aEk", "title": "Windows 10 Gets 5 Years Extended Support With 0patch" },
    { "id": "njdZ0YzoocY", "title": "Fake Windows 11 Government Edition" },
    { "id": "-iIRCWttWb0", "title": "Kaspersky is Now Banned - What You Need to Know" },
    { "id": "4HcNOH7tRiQ", "title": "Do You Make These Stupid PC Mistakes" },
    { "id": "cPKZuqHWB_Q", "title": "Kaspersky Antivirus Software is Banned. How to Remove it" },
    { "id": "TI_5GaKgBMc", "title": "PC Parts You Should NEVER Buy Used" },
    { "id": "KG_sO8N6ut8", "title": "The Windows 11 Start Menu You Have Always Wanted" },
    { "id": "4EXkaf8vkHc", "title": "Recover Deleted Files in Minutes" },
    { "id": "rAdkZG4cUoA", "title": "How to Manage Drivers in Windows" },
    { "id": "h1KGwbmNwZI", "title": "Should You Stop Using Windows 11" },
    { "id": "Tm_gccQFVIo", "title": "Can't Login To Windows 11" },
    { "id": "jMzb0723aoQ", "title": "How To Get Windows Software For Cheap" },
    { "id": "P5wVE1dHNCk", "title": "Windows 11 Group Policy Tips and Tricks" },
    { "id": "mfxszSvHLjc", "title": "Remove Unwanted Software From Windows 11" },
    { "id": "S6DNKM__6pM", "title": "Login to Windows 11 Automatically Without A Password" },
    { "id": "zKVCRmbuRCo", "title": "Mini PC with Built in Touch Screen Display" },
    { "id": "8f7QojSaKiw", "title": "Find Out The Windows Start-up Time" },
    { "id": "vs9oWv3sV8g", "title": "Command Prompt Trick You Need to Know" },
    { "id": "GVdzjtMNVfQ", "title": "Find Out Why Windows 11 PC Won't Boot Up" },
    { "id": "AEDYrLD13HY", "title": "Delete Your Files Like This" },
    { "id": "QF-4cKcEZ0U", "title": "Microsoft Ends Android Apps in Windows 11" },
    { "id": "lhmFBie-wSA", "title": "Best Single Board Computer You Never Heard Of" },
    { "id": "mfyD4XlkRcI", "title": "Reopen An Accidentally Closed Browser Tab" },
    { "id": "mapkFcoeyaE", "title": "Make The Ultimate USB Boot Drive" },
    { "id": "sktGTbh8m44", "title": "How to Configure Windows 11 Home For Gaming" },
    { "id": "buz_LGnnODQ", "title": "Change a Computer's Mac Address in Windows" },
    { "id": "95IviyGC3j4", "title": "Can You Still Use Windows 7 in 2024" },
    { "id": "lAb4-5KKaqg", "title": "Dual Boot Windows and Linux | Step By Step" },
    { "id": "OAHSxVkfJpU", "title": "Free Alternative To The Windows 11 Start Menu" },
    { "id": "TGPedF-MYJo", "title": "Malicious Backdoor Found in Linux" },
    { "id": "HvUx1C3lwuk", "title": "Hidden Windows 11 Feature" },
    { "id": "vCaDguMY_UU", "title": "Can I Use INTEL RAM on AN AMD Motherboard" },
    { "id": "I_wGxRgyxj4", "title": "People Are Still Doing This To Their PC" },
    { "id": "12N0NpaqAa0", "title": "Microsoft Sets Prices for Windows 10 Extended Security Updates" },
    { "id": "N4PCZ2rmx1Q", "title": "Download Any Windows ISO" },
    { "id": "g0WGO_1BjwM", "title": "Microsoft Blocks Customization Apps in Windows 11 Version 24H2" },
    { "id": "ylX6OKQEowI", "title": "A Lite Version Of Windows 11 To Be Released This Year" },
    { "id": "Vo15aCeVGiE", "title": "Stop Microsoft Collecting Data with Portmaster" },
    { "id": "wQSaLIjIQ2E", "title": "Your Home ISP Router Sucks. USE This Instead" },
    { "id": "qj7Vrsgx7rs", "title": "Incognito Mode is Not As Private As You Think" },
    { "id": "OyWWLZu82mI", "title": "Best Ultra-Fast MINI PC You Should Buy | Minisforum EliteMini UM780 XTX" },
    { "id": "W1RUheC4o2w", "title": "Uninstall Microsoft Edge Easily With A Simple Trick" },
    { "id": "2gDPdYuqqUg", "title": "Enhance Your Privacy and Security in Google Chrome" },
    { "id": "m8OJNWW81rs", "title": "The Best Backup Solution For All Your Data" },
    { "id": "h7Kw9hTkh1o", "title": "Don't Buy Ace Magic Mini PC Without Watching This Video" },
    { "id": "eYSfpE-DbpE", "title": "AceMagic Mini PC Comes Pre-Installed With Malware" },
    { "id": "CtG_iO8jztQ", "title": "Windows 10 User? Watch This Video" },
    { "id": "7MUsxgUZMFQ", "title": "Simple Steps To Secure Your NAS" },
    { "id": "NX1PFjwxUZA", "title": "Change These Plex Setting RIGHT NOW" },
    { "id": "oSLPHvURKnc", "title": "Why is This Mini PC So Popular" },
    { "id": "_spc-iVy3tI", "title": "This PC Trick Can Save Your PC" },
    { "id": "fJ_RrL-O57c", "title": "Windows 12 is NOT Happening Yet" },
    { "id": "S4Ho19Z1RUU", "title": "Add More USB Ports To A PC or Laptop" },
    { "id": "OR7k3cbi6LI", "title": "Need A Keyboard? Buy This | The Keychron V2 Max" },
    { "id": "7ZxYPHnTPRc", "title": "Ultimate Guide To Windows 11 Privacy" },
    { "id": "NbmoIwSscZY", "title": "10 Things To Look At When Buying A Used Pre-built PC" },
    { "id": "UfWFjc3JupE", "title": "Got A Nvidia GPU? You NEED The New NVIDIA App" },
    { "id": "RqWGnLmHmJU", "title": "5 Steps To FIX Windows 11" },
    { "id": "IVDfxOtcACs", "title": "How to Check Drive Health and SMART Status in Windows 11" },
    { "id": "hbjxdbvID6Q", "title": "Cool Command Prompt Trick" },
    { "id": "XGFKuxLcs4k", "title": "Very Powerful Geekom A7 Mini PC With Ryzen 9 7940HS" },
    { "id": "624B8nQ8AZU", "title": "Fix Run Error Message In Windows 11" },
    { "id": "x4hp3v-kY5c", "title": "Control Case Fan Speed For Quieter PC" },
    { "id": "tGnD2__SkOI", "title": "6 Steps To Remove Any Virus or Malware For FREE" },
    { "id": "ofJdpvzJK9g", "title": "Make Windows 11 Security Better" },
    { "id": "MEBc6tKsE8M", "title": "Hidden Windows Tool That You Probably Didn't Know" },
    { "id": "5BzO8fofqF0", "title": "Microsoft Wants Copilot AI Everywhere On Windows" },
    { "id": "EJCBdW4l0_0", "title": "Fix Internet Connection Problem in Windows 11" },
    { "id": "ToMJeUPT4po", "title": "Why is Ryzen Power Plan Missing in Windows 11" },
    { "id": "aZq4RuUqYP0", "title": "Everything You Need To Know About Windows Power Plans" },
    { "id": "_4nOc1eBERA", "title": "This Powerful Mini PC is All You Need" },
    { "id": "GUnvAN7ffs4", "title": "Let's Fix Windows 10 After Failed Windows Update" },
    { "id": "Ki0cPLCDrU4", "title": "Awesome Thing To Do With A USB Flash Drive" },
    { "id": "3PkSVrIJNQI", "title": "Why Do We Need Windows Updates" },
    { "id": "hEnAvJOJCeU", "title": "My Computer Was Hacked" },
    { "id": "-vIsyzXOUiE", "title": "5 Best Registry Hacks for Windows 11" },
    { "id": "SHSmOPvQlXQ", "title": "Windows 11 Feature Lets You Reinstall Without Deleting Your Data or Programs" },
    { "id": "zeinxwG54hw", "title": "Things To Know Before You Update The BIOS" },
    { "id": "Xp48T0HLo2s", "title": "How to Repair Windows 11 Without Losing Data or Programs" },
    { "id": "Um3Rh-eHPV8", "title": "Microsoft Make A Massive PC E-Waste Problem With Windows 10" },
    { "id": "Y8bKj5uZhgA", "title": "5 Things To Know Before Optimizing Windows 11" },
    { "id": "d817V1OAoL4", "title": "New Atlas OS for Windows 11 - Optimized for Gaming and Privacy" },
    { "id": "L09v2ETTSOg", "title": "The Best Windows Utility For Windows 11" },
    { "id": "ivf9SByGQTg", "title": "Does This Setting Really Affect Your PC Performance" },
    { "id": "BcsI3Hh3jgE", "title": "How to Improve Your Windows 10 Experience" },
    { "id": "HI623oe-oVo", "title": "Get A Better Windows 11 Start Menu" },
    { "id": "MH9pegT96R0", "title": "Microsoft Finally Lets You Uninstall Edge, Bing, and Cortana" },
    { "id": "iSX60JQZs7g", "title": "Building A NAS On A Budget" },
    { "id": "qdyiBBuqFCM", "title": "Erase Your SSD Securely on Your PC" },
    { "id": "vrQ9x1jfh3w", "title": "Find Security Identifier SID of Any User in Windows 11" },
    { "id": "G1TUWj_qpro", "title": "Does This Software Improve Your Internet Speed" },
    { "id": "jykPPx3Eq3U", "title": "Remove The Home Page From Settings on Windows 11" },
    { "id": "so1HAFV9c-U", "title": "The BEST Tool For Windows 11" },
    { "id": "yOd6T06Y-OY", "title": "Secure Your Computer Data with Hard Drive Encryption" },
    { "id": "Z8N_YUK_DSw", "title": "Automatically Login To Windows Without A Password" }, 
    { "id": "6ydYmqtM1n4", "title": "Turn A Mini PC into A NAS" }, 
    { "id": "hov0P7dad8Q", "title": "Does Optimizing Windows Really Work" }, 
    { "id": "OTUa2_QNrpg", "title": "THIS Tool Makes Windows 11 Better" },
    { "id": "gN6XFnWKCdk", "title": "Stay protected with Windows Security Applocker" },
    { "id": "27IZ1YFMXhY", "title": "Disable Bing Web Search in Windows 11 Start Menu" },
    { "id": "dbYD-WjaXmA", "title": "Chrome Settings You Should Change" },
    { "id": "_ijyASARYeE", "title": "Powerful Mini PC Does Everything You Need" },
    { "id": "AJpLDOsyfvw", "title": "ZimaBlade - This Tiny Server is All You Need" },
    { "id": "PBLD6ZToClA", "title": "Why Can't I Activate Windows?" },
    { "id": "pE3v4c2aZ3A", "title": "How to Fix Unreadable Raw Micro SD Card" },
    { "id": "QBxewPOr91s", "title": "Tools To Tweak Your Windows PC" },
    { "id": "JKLdxh5Q4kQ", "title": "How To Show WiFi Password On Android Phone" },
    { "id": "PX62hGbDES4", "title": "How to Take Screenshots On Your Android Phone" },
    { "id": "eawgHxRpvwQ", "title": "TOTALLY FREE Data Recovery Software To Recover Permanently Deleted Files" }, 
    { "id": "o5wmF25x-ig", "title": "How to Check SSD Lifespan and Health" }, 
    { "id": "ag0SzRCiRPo", "title": "What is the Optimal Virtual Memory Size" }, 
    { "id": "LUoWfNemyFQ", "title": "This Amazing Mini Server is All You Need" }, 
    { "id": "tXOBod_4vwo", "title": "New Windows 11 Feature That Monitors Your System Resources" }, 
    { "id": "SJJQgn45ooY", "title": "Control Automatic Updates on Windows" }, 
    { "id": "57HbrVq6Ej0", "title": "Fix Any .NET Framework Errors in Windows" }, 
    { "id": "WnfrJIWF2LI", "title": "Hidden “Emergency Restart” Feature in Windows" }, 
    { "id": "Xjr6YtimkUw", "title": "How to Clear Windows Defender Protection History in Windows 11" }, 
    { "id": "rer5POB5LdE", "title": "This USB Device Will Help To Repair Your PC" }, 
    { "id": "g9HtnjZuPQs", "title": "First Thing to Change in Windows 11" }, 
    { "id": "uYe5mFSwOlY", "title": "The End Of Windows 10" }, 
    { "id": "_rNPHLUcJ28", "title": "Is Atlas OS Worth it" }, 
    { "id": "etd6JDW-TKM", "title": "Customize Your Windows 11 Settings With This Tool" }, 
    { "id": "4rTbJ9o9LoY", "title": "How to Disable Windows S Mode Without Internet" }, 
    { "id": "FxxwAU-Zg3Q", "title": "Reset Forgotten Windows 11 Password For Free" }, 
    { "id": "BaAm5dbO5N0", "title": "Do This After Installing Windows 11" }, 
    { "id": "-tIO4B8q8sk", "title": "Create Custom Windows 10 Image With Applications Pre-installed" }, 
    { "id": "Bc0ubbeFKlY", "title": "Setup Your Own Broadband Speed Test Server" }, 
    { "id": "mUu7wMK7-HE", "title": "How to Cut A Snippet of Video in VLC Media Player" }, 
    { "id": "uRsBpDR2CNg", "title": "Disable Windows 11 Services You Don't Need" }, 
    { "id": "PsyC76KwsCw", "title": "Choosing the Right PC Power Supply (PSU) Power Supply Buyers Guide" }, 
    { "id": "wirNqYS1UNQ", "title": "How to Repair Microsoft Edge to Fix Problems in Windows 10" }, 
    { "id": "zjGwC1H29gw", "title": "Best Budget Airflow PC Case | Nova Mesh SE TG ARGB" }, 
    { "id": "aIXDD4NKx60", "title": "Disable Unnecessary Services in Windows 10 in 2021" }, 
    { "id": "Jg4h1uUB2Yk", "title": "How to Turn Off Windows 10 Data Collection" }, 
    { "id": "oaZWVg0zq7s", "title": "Remove All Built in Windows 10 Apps" }, 
    { "id": "sXfriVBVF-g", "title": "How to Fix MSVCP140.dll is Missing on Windows 10" }, 
    { "id": "K_CLVVlq1KY", "title": "How to Block Remote Access Software Sites" }, 
    { "id": "f-xCfS8unLw", "title": "Dual Boot Windows 10 and Android Phoenix OS" }, 
    { "id": "C5aXI_lsGxg", "title": "Make Windows 10 Faster and Improve Performance" }, 
    { "id": "Sbm2YcdjL2o", "title": "How to Check Hard Drive Health in Windows 10" }, 
    { "id": "W68o0IKe4DY", "title": "Solve PC Problems Over A Remote Connection" }, 
    { "id": "VRnoqCK-6Gc", "title": "Protect Your PC From Potentially Unwanted Applications" }, 
    { "id": "py4U2YI7V4c", "title": "Best Tool to Tweak and Customize Windows 10" }, 
    { "id": "_RDxU7l05Nw", "title": "How to Get Microsoft Office for Free" }, 
    { "id": "tXu3isGqHNk", "title": "15 Windows System Tools You Must Have" }, 
    { "id": "JRyXTSHYG5A", "title": "Make Your Linux Desktop Look Awesome" }, 
    { "id": "191hvsaqpIw", "title": "How to Test Internet Speed in Command Line" }, 
    { "id": "z3cjTqCQemU", "title": "How to Clear All Cache in Windows 10" }, 
    { "id": "XpyhgTOXY18", "title": "How to Speed Up and Upgrade an Old, Slow Laptop" }, 
    { "id": "FgvvEh9Kg-Q", "title": "How to Enable File Explorer Dark Mode on Windows 10" }, 
    { "id": "AwHGlBkWQ_A", "title": "How to Clear Cache in Microsoft Office" }, 
    { "id": "1uLhfF27VA8", "title": "Remove Photo Background for Free in Seconds" }, 
    { "id": "n17jVB5uQdQ", "title": "Turn Off This Wi-Fi Setting Right Now" }, 
    { "id": "TGgrqqXvISU", "title": "This Windows Setting Will Monitor PC Performance" }, 
    { "id": "nXpHLw5mDNg", "title": "Don't Get Hacked Like Linus Tech Tips" }
  ],
  "playlists": [
    
  ]
}
