{
  "channel": {
    "id": "java0405",
    "name": "김기태의 JAVA를 자바",
    "profile": "https://yt3.googleusercontent.com/ytc/AGIKgqMh8ogxxf_Q1gazM9FTAxRmL3ABD8ACNtCZWrV9=s176-c-k-c0x00ffffff-no-rj",
    "banner": "https://yt3.googleusercontent.com/nYBM4tFv0FucvhrpQPedLqqK-VabAD9T3p0aLzwZchtwSVMKwyXP77Un7hQs1AbiEVEVHARWVss=w1060-fcrop64=1,00005a57ffffa5a8-k-c0xffffffff-no-nd-rj"
  },
  "videos": [
    { "id": "gwf7ajh7Uf8", "title": "23년 고급알고리즘 2장-4" },
    { "id": "PCtWPGc_r20", "title": "23년 고급알고리즘 2장-3" },
    { "id": "zzrmfk-whlU", "title": "23년 고급알고리즘 2장-2" },
    { "id": "dmNskcJDiyA", "title": "23년 고급알고리즘 2장-1" },
    { "id": "rxRWXgSFxxk", "title": "23년 테스팅응용(9) V-모델이란?" },
    { "id": "5N2tSLVSXAI", "title": "23년 테스팅응용(8) 테스팅의 심리학" },
    { "id": "V6FT3_NK8K4", "title": "23년 테스팅응용(7) 테스트 완료 조건" },
    { "id": "gRiScyrMIJ8", "title": "23년 테스팅응용(6) 테스트 프로세스 기초" },
    { "id": "XZkgSR9Z1s8", "title": "23년 2학기 스프링부트3 : DI- IoC(xml 사용)" },
    { "id": "a6hV1MinsaA", "title": "23년 2학기 스프링부트2 : DI- IoC(인터페이스 사용)" },
    { "id": "ZtiY6MmXlmw", "title": "23년 2학기 스프링부트1 : DI- IoC(기본 사용)" },
    { "id": "NucbvUu8Ksw", "title": "스레드1" }, 
    { "id": "oHOLCzXCpNU", "title": "스레드2" }, 
    { "id": "qRiUNQgD4s8", "title": "스레드3" }, 
    { "id": "vY3fDgsw7xE", "title": "스레드4" }, 
    { "id": "UxUF_9peVpA", "title": "(2022년 2학기)스프링 부트 쇼핑몰 프로젝트15" }, 
    { "id": "bDERi0U8dXA", "title": "(2022년 2학기)스프링 부트 쇼핑몰 프로젝트16" }, 
    { "id": "DzZc4EQVCeE", "title": "(2022년 2학기)스프링 부트 쇼핑몰 프로젝트17" }, 
    { "id": "IbRKT1D5yV4", "title": "(2022년 2학기)스프링 부트 쇼핑몰 프로젝트20" }, 
    { "id": "GP1sdX81MFc", "title": "(2022년 2학기)스프링 부트 쇼핑몰 프로젝트22" }, 
    { "id": "njCsrBdZqv8", "title": "(2022년 2학기)스프링 부트 쇼핑몰 프로젝트28" }, 
    { "id": "C32n7Do3BdU", "title": "Swing 6주차 4" }, 
    { "id": "P6wOCuoBuO4", "title": "Swing 7주차 3" }, 
    { "id": "oPfZrTfAkE4", "title": "TOC7 JGraphT사용하기(설명)" }, 
    { "id": "FkowGcWHVCw", "title": "TOC8 JGraphT사용하기(오류 수정)"  } 
  ]
}
