{
  "channel": {
    "id": "programmersdevcourse",
    "name": "프로그래머스 데브코스",
    "profile": "https://yt3.googleusercontent.com/-59SPUbTVwOhmGrubN3yBfbfLVnIDEh28np-KZdT0HRTRWo5LOHUcM4CvkYoJfQ-rZdApxTP4Q=s176-c-k-c0x00ffffff-no-rj",
    "banner": "https://yt3.googleusercontent.com/qLoMFwH7uSKEConDQDhGdHtut3dFzW0i2nACdMRTVs4SezhmYJf2vCBEsLMBZ9E2JWasJDtn=w1707-fcrop64=1,00005a57ffffa5a8-k-c0xffffffff-no-nd-rj"
  },
  "videos": [
    { "id": "SKdvm3eP7cU", "title": "조재훈 - JS의 this｜프론트엔드 데브코스 5기 딥다이브｜231109" },
    { "id": "K0zVppRK9eU", "title": "손호민 - 어떻게 Next.js는 성장했는가?｜프론트엔드 데브코스 5기 딥다이브｜231204" },
    { "id": "Rfd9FM2ue78", "title": "김석주 - API에 대해 프리젠테이션 하나로 이해 하는 시간｜프론트엔드 데브코스 5기 딥다이브｜231208" },
    { "id": "CiNrMZYtQDI", "title": "신준혁 - React 렌더링 최적화와 렌더링 관계 트리｜프론트엔드 데브코스 5기 딥다이브｜231229" },
    { "id": "DHTzZGmQjSU", "title": "김석주 - 이전에 하지 않았던 일들을 하면서 일어난 변화｜프론트엔드 데브코스 5기 딥다이브｜231102" },
    { "id": "4wF_DxRSP78", "title": "조익준 - 개발자관계론｜프론트엔드 데브코스 5기 딥다이브｜240103" },
    { "id": "0A0_cXY6cGc", "title": "오원주 - 당신은 useEffect가 필요 없을 수도 있습니다.｜프론트엔드 데브코스 5기 딥다이브｜231206" },
    { "id": "A7TdqonLL7I", "title": "프론트x백엔드 데브코스 5기 - 키윙 - 팀3 삼시세코" },
    { "id": "IkP7eGEUlok", "title": "프론트x백엔드 데브코스 5기 - 혼터뷰 - 팀4 아이육" },
    { "id": "QuHfWICoV-4", "title": "프론트x백엔드 데브코스 5기 - 알고바로 - 팀5 이리오이소" },
    { "id": "Pn32wai9vCk", "title": "프론트x백엔드 데브코스 5기 - 사이드픽 - 팀6 육개짱" },
    { "id": "R7LdzAIckMY", "title": "자율주행 데브코스 Planning&Control 2기 | 모라이 시뮬레이터 자율주행 랩타임 경진대회 프로젝트 | 노다현, 류재웅" },
    { "id": "WyLPbwMUGpg", "title": "자율주행 데브코스 Planning&Control 2기 | 모라이 시뮬레이터 자율주행 랩타임 경진대회 프로젝트 | 김혜성, 민경원, 황지선" },
    { "id": "Vdvu3hllLAY", "title": "자율주행 데브코스 Planning&Control 2기 | 모라이 시뮬레이터 자율주행 랩타임 경진대회 프로젝트 | 이환수, 임정혁, 김예지, 정성인" },
    { "id": "LfHA7IpBgpU", "title": "자율주행 데브코스 Planning&Control 2기 | 모라이 시뮬레이터 자율주행 랩타임 경진대회 프로젝트 | 장주영, 박정훈, 조한흠" },
    { "id": "3bMYyQe-JSI", "title": "김별이 - JAVA 17까지의 변화 | 백엔드 데브코스 5기 | 20231012" },
    { "id": "e63clnev_vE", "title": "프론트엔드x백엔드 데브코스 5기 - 동구라미 - 팀7 고고링" },
    { "id": "p9BoInilUxI", "title": "프론트엔드x백엔드 데브코스 5기 - LocoMoco - 팀8 로코모코" },
    { "id": "2KzKHFIiCVw", "title": "프론트엔드x백엔드 데브코스 5기 - 핸즈업 - 팀10 핸즈업" },
    { "id": "v37lEi4NNNA", "title": "프론트엔드x백엔드 데브코스 5기 - 모각Go! - 팀9 눈떠보니 개발자" },
    { "id": "4T5poQwI1eU", "title": "프론트엔드x백엔드 데브코스 5기 - 짤뮤니티 - 팀12 십이간지" },
    { "id": "dSMVSfEQKtI", "title": "박유진 - Test Double | 백엔드 데브코스 5기 | 20231013" },
    { "id": "MYf-30vzTZA", "title": "자율주행 데브코스 Planning&Control 2기 | 서빙로봇 프로젝트 | 이재호" },
    { "id": "6tCF624q5sg", "title": "자율주행 데브코스 Planning&Control 2기 | 서빙로봇 프로젝트 | 이환수" },
    { "id": "Ud91DvdqAJM", "title": "자율주행 데브코스 Planning&Control 2기 | 서빙로봇 프로젝트 | 박정훈" },
    { "id": "k6KT8SJWoec", "title": "자율주행 데브코스 Planning&Control 2기 | 서빙로봇 프로젝트 | 민경원" },
    { "id": "ssHYcHMvjgo", "title": "박병규 - 자바스크립트 실행 컨텍스트 | 웹 풀 사이클 데브코스 1기 Dev-Course Talk | 240118" },
    { "id": "wFNOTRuLFVk", "title": "안지환 - 브라우저에 www.google.com 검색 시 웹 페이지를 볼때까지 과정 | 웹 풀 사이클 데브코스 1기 Dev-Course Talk | 240118" },
    { "id": "B1n0yg5AfPI", "title": "김홍래 - package manager | 웹 풀 사이클 데브코스 1기 Dev-Course Talk | 240118" },
    { "id": "3L9mhA-HH-Y", "title": "김진환 - API 명세서 작성 | 웹 풀 사이클 데브코스 1기 Dev-Course Talk | 240118" },
    { "id": "wdPxPmPvMOg", "title": "이창근 - JS prototype | 웹 풀 사이클 데브코스 1기 Dev-Course Talk | 240111" },
    { "id": "w7x5qj7zfho", "title": "장광진 - 호이스팅 | 웹 풀 사이클 데브코스 1기 Dev-Course Talk | 240111" },
    { "id": "oenRakCSJK8", "title": "하종훈 - JS 빌트인 객체(컬렉션 제외) | 웹 풀 사이클 데브코스 1기 Dev-Course Talk | 240111" },
    { "id": "RCLQh9xymRA", "title": "박상하 - 자바스크립트 set, map, array | 웹 풀 사이클 데브코스 1기 Dev-Course Talk | 240111" },
    { "id": "X_YJLLilx3A", "title": "황성택 - DB 정규화 | 웹 풀사이클 데브코스 1기 Dev-Course Talk | 240125" },
    { "id": "bRWzO7dajc4", "title": "이의진 - 프론트엔드의 캐싱 | 웹 풀사이클 데브코스 1기 Dev-Course Talk | 240125" },
    { "id": "PrZqqfxM2bE", "title": "홍시현 - 비동기 함수 | 웹 풀사이클 데브코스 1기 Dev-Course Talk | 240201" },
    { "id": "JKMh3gBPHzs", "title": "황재경 - REST API | 웹 풀사이클 데브코스 1기 Dev-Course Talk | 240201" },
    { "id": "avEEaKqn74U", "title": "신원익 - clustured index와 non-clustered index의 차이 | 웹 풀사이클 데브코스 1기 Dev-Course Talk | 240125" },
    { "id": "-CjbEP0Adf8", "title": "자율주행 데브코스 Perception 6기 | 최종 프로젝트 발표회 I 솔져76" },
    { "id": "aBR9F8LQe44", "title": "자율주행 데브코스 Perception 6기 | 최종 프로젝트 발표회 I 기타등등" },
    { "id": "MbakEi_26TU", "title": "자율주행 데브코스 Perception 6기 | 최종 프로젝트 발표회 I FUMA : FUsion MAsters" },
    { "id": "aT5MMAoZ3yU", "title": "자율주행 데브코스 Perception 6기 | 최종 프로젝트 발표회 I 형사나사" },
    { "id": "Mm2tCwWYfjw", "title": "자율주행 데브코스 Perception 6기 | 딥러닝 프로젝트 | Rolling in the deep" },
    { "id": "WgtIqllFLhs", "title": "자율주행 데브코스 Perception 6기 | 딥러닝 프로젝트 | Learning Machine" },
    { "id": "9B98Sm3rMd4", "title": "자율주행 데브코스 Perception 6기 | 딥러닝 프로젝트 | “정훈이 없는” 정훈팀" },
    { "id": "1BsIGArCXCU", "title": "자율주행 데브코스 Perception 6기 | 딥러닝 프로젝트 | 딮잉소스Deep ing source" },
    { "id": "pVbXkA6nZJA", "title": "데이터 엔지니어링 데브코스 2기 | 스트리머의 게임 방송과 게임 흥행 사이의 관계 | 2팀 1조" },
    { "id": "ipjIjPob1N8", "title": "데이터 엔지니어링 데브코스 2기 | 드라마 흥행정도 예측과 드라마 관련주 투자 분석 | 3팀 2조" },
    { "id": "XSzYhxV4jN8", "title": "데이터 엔지니어링 데브코스 2기 | “Stock sight\" 실시간 일간 주식 데이터 서비스 | 4팀 3조" },
    { "id": "dm8-WQOrm4c", "title": "데이터 엔지니어링 데브코스 2기 | 최저가 유튜브 레시피 검색 서비스 | 6팀 1조" },
    { "id": "VQgZw2elr38", "title": "데이터 엔지니어링 데브코스 2기 | 여행지 추천 및 계획 수립 웹 서비스 | 6팀 2조" },
    { "id": "FP_FBbL5Zmk", "title": "데이터 엔지니어링 데브코스 2기 | 금융 데이터 분석 환경 구축 | 1팀 1조" },
    { "id": "Lj48wmTn49A", "title": "데이터 엔지니어링 데브코스 2기 | Foodpalette 맛집 추천(검색) | 4팀 1조" },
    { "id": "D738H2ntHcY", "title": "데이터 엔지니어링 데브코스 2기 | 영화 뭐 보지? | 4팀 2조" },
    { "id": "-L67h3t2k74", "title": "데이터 엔지니어링 데브코스 2기 | 나에게 가장 잘 맞는 자치구는? | 5팀 1조" },
    { "id": "0UIxemBX8Ow", "title": "데이터 엔지니어링 데브코스 2기 | 실시간 교통사고와 날씨 데이터 분석 대시보드 구현 | 3팀 1조" },
    { "id": "wI3dKUNpNE0", "title": "프론트x백엔드 데브코스 4기 - 모아밤 - 팀15 모아밤" },
    { "id": "kdLLDi0teZg", "title": "프론트x백엔드 데브코스 4기 - 픽플(Pickple) - 팀16 자바와 스크립트" },
    { "id": "I6jlFYTw2u0", "title": "프론트x백엔드 데브코스 4기 - 스테디(Steady) - 팀13 블리츠" },
    { "id": "4-p4-ENMZ8Y", "title": "프론트x백엔드 데브코스 4기 - 커피밋(Coffee Meet) - 팀14 까또즈" },
    { "id": "Rmb_8xf45Mo", "title": "프론트x백엔드 데브코스 4기 - 이력, 써 - 팀11 0ㅏ몬드빼빼로" },
    { "id": "BywmSt9GK7o", "title": "프론트x백엔드 데브코스 4기 - 리뷰레인저 - 팀12 일리네어" },
    { "id": "QWP9MR-d7tY", "title": "프론트x백엔드 데브코스 4기 - 스터데이(Studay) - 팀9 구찡" },
    { "id": "QoQm6M8QSHE", "title": "프론트x백엔드 데브코스 4기 - LinkHub - 팀10 텐텐" },
    { "id": "GVe8yh769Yg", "title": "프론트x백엔드 데브코스 4기 - OneDayHero - 팀6 6 Heroes" },
    { "id": "fWwrTELXxKI", "title": "프론트x백엔드 데브코스 4기 - 애니프렌즈 - 팀7 Clova" },
    { "id": "n2ZQRHF85F4", "title": "프론트x백엔드 데브코스 4기 - 우리이거삭제하지말자 - 팀5 4K" },
    { "id": "fNK_vLHnkwM", "title": "프론트x백엔드 데브코스 4기 - 올해도 아좌좌 - 팀3 뉴바람스(New Barams)" },
    { "id": "81bYaF4Euic", "title": "프론트x백엔드 데브코스 4기 - 딜라잇(Dealight) - 팀8 팔팔해" },
    { "id": "Fg_rhOSmyxQ", "title": "프론트x백엔드 데브코스 4기 - 스클(Space Club) - 팀4 Skrrr" },
    { "id": "nlQEfRSlbEU", "title": "프론트x백엔드 데브코스 4기 - 버킷백 - 팀2 붉은장미" },
    { "id": "9TX9TS0o3KI", "title": "소승수 - 왜 System out println 대신 log를 써야할까 | 백엔드 데브코스 5기 | 20231205" },
    { "id": "_n9zKCs5yMs", "title": "김용상 - DB Index | 백엔드 데브코스 5기 | 20231012" },
    { "id": "_n9zKCs5yMs", "title": "김용상 - DB Index | 백엔드 데브코스 5기 | 20231012" },
    { "id": "9rns2MEYEdw", "title": "인공지능 데브코스 6기 -풍경 사진 방해하는 간판 커스텀하기(AIC팀)" },
    { "id": "TKRMjQwHs_s", "title": "인공지능 데브코스 6기 -아기 모니터링 시스템(KoreaYunzee팀)" },
    { "id": "ZHB_oBT5eeA", "title": "인공지능 데브코스 6기 -진열대 상품 가격표 인식을 통한 최저가 사이트 제공(Pingu팀)" },
    { "id": "0K_Pa_8EjOg", "title": "인공지능 데브코스 6기 -원하는 mbti로 바꿔드립니다.(아이즈팀)" },
    { "id": "I_bnnTaOqTg", "title": "인공지능 데브코스 6기 -Review The Review(hoT6팀)" },
    { "id": "Y9yJAAwiu-M", "title": "인공지능 데브코스 6기 -cartoontts(LEGO팀)" },
    { "id": "6-gG6KDx2b8", "title": "김대휘 - Equals와 hashCode | 백엔드 데브코스 5기 | 20231011" },
    { "id": "qdoKvvwDq5U", "title": "김강훈 - Exception | 백엔드 데브코스 5기 | 20231011" },
    { "id": "Vr5tUINDGeU", "title": "김남규  - SOLID 객체지향 개발 원칙 | 백엔드 데브코스 5기 | 20231011" },
    { "id": "nEW0Dmi2E9o", "title": "정의진 - Controller Advice와 Spring 예외처리 | 백엔드 데브코스 5기 | 20231207" },
    { "id": "T6QQeX1cIiY", "title": "남은찬  - 자바 프록시 패턴 | 백엔드 데브코스 5기 | 20231011" },
    { "id": "OmiI9TC_PS4", "title": "최인준 - 싱글턴 패턴 | 백엔드 데브코스 5기 | 20231013" },
    { "id": "PB4m4d8BdUk", "title": "이중원 - Stream | 백엔드 데브코스 5기 | 20231012" },
    { "id": "G9oy2_vuU9Y", "title": "김현우 - 스프링 AOP 알고 쓰니? | 백엔드 데브코스 5기 | 20231207" },
    { "id": "Q3QGC-Llqr8", "title": "엄예림 - DTO | 백엔드 데브코스 5기 | 20231205" },
    { "id": "lp4WOiOqDvo", "title": "이중원 - Spring Transaction & JPA | 백엔드 데브코스 5기 | 20231205" },
    { "id": "zv9xm0Np0L4", "title": "남은찬 - Spring Test Annotation | 백엔드 데브코스 5기 | 20231207" },
    { "id": "uWpJpm-aO2Y", "title": "송인재 - 연관관계 매핑 | 백엔드 데브코스 5기 | 20231205" },
    { "id": "QQP_auuBTDA", "title": "김주환 - Java Generic | 백엔드 데브코스 5기 | 20231013" },
    { "id": "9n8w3EqSQOg", "title": "임수진 - Optional | 백엔드 데브코스 5기 | 20231012" },
    { "id": "dSMVSfEQKtI", "title": "박유진 - Test Double | 백엔드 데브코스 5기 | 20231013" },
    { "id": "tFC6_6oeyv8", "title": "김주웅 - 자바 8과 자바 17의 차이 | 백엔드 데브코스 4기 | 20230628" },
    { "id": "VmWscKw6eSw", "title": "김범석  - String 그리고 Constant Pool | 백엔드 데브코스 4기 | 20230614" },
    { "id": "s9Cm3TxwdZI", "title": "고예성 - 동적 바인딩과 정적 바인딩 | 백엔드 데브코스 4기 | 20230614" },
    { "id": "5nAUcCBCKuU", "title": "문종운 - 익명클래스와 람다 | 백엔드 데브코스 4기 | 20230614" },
    { "id": "m_b5PLwYtsY", "title": "홍창기 - XSS(Cross-Site-Scripting) Attack｜프론트엔드 데브코스 4기 딥다이브｜20230828" },
    { "id": "WuP-FygaIdM", "title": "김유진 - 방황과 마주하기까지의 여정｜프론트엔드 데브코스 4기 딥다이브｜20230920" },
    { "id": "uzbwNUMPBNg", "title": "홍창기 - Promise to async / await｜프론트엔드 데브코스 4기 딥다이브｜20230727" },
    { "id": "PXuE5MhJMiE", "title": "남궁호수 - 실행 컨텍스트와 다양한 상황에서의 this｜프론트엔드 데브코스 4기 딥다이브｜20230731" },
    { "id": "J7S7R2aM6Bo", "title": "이종길 - 불변성｜프론트엔드 데브코스 4기 딥다이브｜20230616" },
    { "id": "57CtedBA7Kk", "title": "이정욱 - Three.js｜프론트엔드 데브코스 4기 딥다이브｜20230831" },
    { "id": "6OMkqhfKVF0", "title": "이범진 - 다이나믹 프로그래밍 접근법｜프론트엔드 데브코스 4기 딥다이브｜20230630" },
    { "id": "3fd2FiTPkgA", "title": "이상훈 - 프로토타입｜프론트엔드 데브코스 4기 딥다이브｜20230726" },
    { "id": "ZEI0QrIIW8U", "title": "프로그래머스 데브코스 미리보기: 타입스크립트로 함께하는 웹 풀 사이클 개발(React, Node.js) (with CLOVA Dubbing)" }
  ]
}