{
  "channel": {
    "id": "SergioBecerril",
    "name": "Sergio Becerril",
    "profile": "https://yt3.googleusercontent.com/ytc/AGIKgqOVZPYHXRLIm-kdDpDH2U9fhQqzLcXMMQkgRZQMzQ=s176-c-k-c0x00ffffff-no-rj",
    "banner": "https://yt3.googleusercontent.com/0Esl6flOQS-BlZiWf94Pu1tHJ3lEftCvwN_2vgKwGBwLrnZRkpVx1KJVjXDm9je7jY2u-O3V0w=w1707-fcrop64=1,00005a57ffffa5a8-k-c0xffffffff-no-nd-rj"
  },
  "videos": [
    { "id": "lzkonCgJ_M0", "title": "🔥 Tutorial: Crear tarjeta animada con SwiftUI. Aprende a crear una animación con SwiftUI" },
    { "id": "j0GzxODj4WA", "title": "🚀 Colecciones en Swift. Clase extraída de mi programa iOS Extreme. ¡Aún estás a tiempo de entrar!" },
    { "id": "jFC0wBL6OPY", "title": "📅 Aprende a crear una App iOS desde cero | Crea una aplicación de tareas con SwiftUI 🚀 4/4" },
    { "id": "ooVUEx7GMqs", "title": "🤓 Te presento mi programa de Mentoría iOS Extreme🔥Aprende a crear Apps para iOS de forma profesional" },
    { "id": "PZ1CUhIb1Io", "title": "🧨 ¿Qué es Combine? | Iniciación a el Framework de programación reactiva Combine 🤓 | Concurrencia iOS" },
    { "id": "DVWs2yMnYEg", "title": "👨🏻‍💻 Taller de iniciación iOS: Extreme App 👊🏽 | Sesión 1 de 3. Iníciate en el desarrollo de Apps 🔥" },
    { "id": "0Ul4hxMGEj0", "title": "👨🏻‍💻 Taller básico iOS: Extreme App 👊🏽 | Sesión 2 de 3. Empieza a crear Apps de forma profesional 🔥" },
    { "id": "p3-osr04GSM", "title": "📅 Aprende a crear una App iOS desde cero | Crea una aplicación de tareas con SwiftUI 🚀 1/4" },
    { "id": "xgmCjPG-HeI", "title": "🚀 Curso práctico iOS | Crea una App de BBDD de películas con MVVM y RxSwift - Xcode13 y Swift 5.5" }
  ]
}

